nrsur_catalog/__init__.py
nrsur_catalog/cache.py
nrsur_catalog/catalog.py
nrsur_catalog/logger.py
nrsur_catalog/lvk_posterior.py
nrsur_catalog/nrsur_result.py
nrsur_catalog/style.mplstyle
nrsur_catalog/style.py
nrsur_catalog/api/__init__.py
nrsur_catalog/api/download_event.py
nrsur_catalog/api/generate_url_file.py
nrsur_catalog/api/lvk_urls.txt
nrsur_catalog/api/nrsur_urls.txt
nrsur_catalog/api/urls.py
nrsur_catalog/api/zenodo_interface.py
nrsur_catalog/utils/__init__.py
nrsur_catalog/utils/constants.py
nrsur_catalog/utils/convert_result_json_to_hdf5.py
nrsur_catalog/utils/overlaid_corner.py
nrsur_catalog/utils/pesummary_result_to_bilby_result.py
nrsur_catalog-0.0.5.dist-info/METADATA
nrsur_catalog-0.0.5.dist-info/WHEEL
nrsur_catalog-0.0.5.dist-info/entry_points.txt
nrsur_catalog-0.0.5.dist-info/top_level.txt
nrsur_catalog-0.0.5.dist-info/zip-safe
nrsur_catalog-0.0.5.dist-info/RECORD
